videodb/__about__.py
videodb/__init__.py
videodb/_constants.py
videodb/_upload.py
videodb/asset.py
videodb/audio.py
videodb/client.py
videodb/collection.py
videodb/exceptions.py
videodb/image.py
videodb/scene.py
videodb/search.py
videodb/shot.py
videodb/timeline.py
videodb/video.py
videodb/_utils/__init__.py
videodb/_utils/_http_client.py
videodb/_utils/_video.py
videodb-0.2.8.dist-info/LICENSE
videodb-0.2.8.dist-info/METADATA
videodb-0.2.8.dist-info/WHEEL
videodb-0.2.8.dist-info/top_level.txt
videodb-0.2.8.dist-info/RECORD
